{
  "model_version": "v2_multilingual_cased",
  "base_model": "distilbert-base-multilingual-cased",
  "test_set_type": "real_world",
  "test_set_size": 52,
  "exact_match_count": 34,
  "exact_match_ratio": 0.6538461538461539,
  "token_level_metrics": {
    "accuracy": 0.9140625,
    "precision_weighted": 0.9199724748770476,
    "recall_weighted": 0.9140625,
    "f1_weighted": 0.9101114738126457,
    "precision_macro": 0.939049727646721,
    "recall_macro": 0.8554920828428035,
    "f1_macro": 0.8834620642502848
  },
  "confusion_matrix": [
    [
      14,
      1,
      0,
      1,
      0,
      1,
      5,
      0,
      0
    ],
    [
      0,
      45,
      2,
      0,
      0,
      0,
      0,
      0,
      0
    ],
    [
      0,
      0,
      62,
      0,
      0,
      0,
      0,
      0,
      0
    ],
    [
      0,
      0,
      1,
      30,
      0,
      0,
      0,
      0,
      0
    ],
    [
      0,
      0,
      0,
      0,
      0,
      0,
      0,
      0,
      0
    ],
    [
      0,
      0,
      0,
      0,
      0,
      41,
      0,
      0,
      0
    ],
    [
      0,
      0,
      0,
      0,
      0,
      7,
      26,
      0,
      0
    ],
    [
      0,
      1,
      0,
      0,
      0,
      0,
      0,
      12,
      0
    ],
    [
      0,
      0,
      3,
      0,
      0,
      0,
      0,
      0,
      4
    ]
  ],
  "labels": [
    "O",
    "B-TITLE",
    "I-TITLE",
    "B-YEAR",
    "I-YEAR",
    "B-QUALITY",
    "I-QUALITY",
    "B-ARTIST",
    "I-ARTIST"
  ],
  "errors": [
    {
      "filename": "Trainspotting.1996.1080p.BluRay.x264-CtrlHD.mkv",
      "preprocessed": "Trainspotting 1996 1080p BluRay x264 CtrlHD",
      "true": [
        "B-TITLE",
        "B-YEAR",
        "B-QUALITY",
        "I-QUALITY",
        "I-QUALITY",
        "O"
      ],
      "pred": [
        "B-TITLE",
        "B-YEAR",
        "B-QUALITY",
        "I-QUALITY",
        "I-QUALITY",
        "I-QUALITY"
      ]
    },
    {
      "filename": "No.Country.for.Old.Men.2007.2160p.UHD.BluRay.HEVC.mkv",
      "preprocessed": "No Country for Old Men 2007 2160p UHD BluRay HEVC",
      "true": [
        "B-TITLE",
        "I-TITLE",
        "I-TITLE",
        "I-TITLE",
        "I-TITLE",
        "B-YEAR",
        "B-QUALITY",
        "O",
        "I-QUALITY",
        "I-QUALITY"
      ],
      "pred": [
        "B-TITLE",
        "I-TITLE",
        "I-TITLE",
        "I-TITLE",
        "I-TITLE",
        "B-YEAR",
        "B-QUALITY",
        "I-QUALITY",
        "I-QUALITY",
        "I-QUALITY"
      ]
    },
    {
      "filename": "Drive.2011.1080p.BluRay.DTS.x264-EbP.mkv",
      "preprocessed": "Drive 2011 1080p BluRay DTS x264 EbP",
      "true": [
        "B-TITLE",
        "B-YEAR",
        "B-QUALITY",
        "I-QUALITY",
        "O",
        "I-QUALITY",
        "O"
      ],
      "pred": [
        "B-TITLE",
        "B-YEAR",
        "B-QUALITY",
        "I-QUALITY",
        "I-QUALITY",
        "I-QUALITY",
        "O"
      ]
    },
    {
      "filename": "Sicario_2015_BDRip_1080p.avi",
      "preprocessed": "Sicario 2015 BDRip 1080p",
      "true": [
        "B-TITLE",
        "B-YEAR",
        "B-QUALITY",
        "I-QUALITY"
      ],
      "pred": [
        "B-TITLE",
        "B-YEAR",
        "B-QUALITY",
        "B-QUALITY"
      ]
    },
    {
      "filename": "Gone.Girl.2014.WEB-DL.1080p.x265.mkv",
      "preprocessed": "Gone Girl 2014 WEB DL 1080p x265",
      "true": [
        "B-TITLE",
        "I-TITLE",
        "B-YEAR",
        "B-QUALITY",
        "I-QUALITY",
        "I-QUALITY",
        "I-QUALITY"
      ],
      "pred": [
        "B-TITLE",
        "I-TITLE",
        "B-YEAR",
        "B-QUALITY",
        "I-QUALITY",
        "B-QUALITY",
        "I-QUALITY"
      ]
    },
    {
      "filename": "The.Matrix.1999.4K.UHD.BluRay.HEVC.mkv",
      "preprocessed": "The Matrix 1999 4K UHD BluRay HEVC",
      "true": [
        "B-TITLE",
        "I-TITLE",
        "B-YEAR",
        "B-QUALITY",
        "O",
        "I-QUALITY",
        "I-QUALITY"
      ],
      "pred": [
        "B-TITLE",
        "I-TITLE",
        "B-YEAR",
        "B-QUALITY",
        "I-QUALITY",
        "I-QUALITY",
        "I-QUALITY"
      ]
    },
    {
      "filename": "Interstellar (2014).mkv",
      "preprocessed": "Interstellar (2014)",
      "true": [
        "B-TITLE",
        "B-YEAR"
      ],
      "pred": [
        "B-TITLE",
        "I-TITLE"
      ]
    },
    {
      "filename": "Иван.Васильевич.меняет.профессию.1973.BDRip.1080p.mkv",
      "preprocessed": "Иван Васильевич меняет профессию 1973 BDRip 1080p",
      "true": [
        "B-TITLE",
        "I-TITLE",
        "I-TITLE",
        "I-TITLE",
        "B-YEAR",
        "B-QUALITY",
        "I-QUALITY"
      ],
      "pred": [
        "B-TITLE",
        "I-TITLE",
        "I-TITLE",
        "I-TITLE",
        "B-YEAR",
        "B-QUALITY",
        "B-QUALITY"
      ]
    },
    {
      "filename": "Чебурашка.2023.WEB-DL.1080p.mkv",
      "preprocessed": "Чебурашка 2023 WEB DL 1080p",
      "true": [
        "B-TITLE",
        "B-YEAR",
        "B-QUALITY",
        "I-QUALITY",
        "I-QUALITY"
      ],
      "pred": [
        "B-TITLE",
        "B-YEAR",
        "B-QUALITY",
        "I-QUALITY",
        "B-QUALITY"
      ]
    },
    {
      "filename": "Левиафан-2014-BluRay-1080p.mkv",
      "preprocessed": "Левиафан 2014 BluRay 1080p",
      "true": [
        "B-TITLE",
        "B-YEAR",
        "B-QUALITY",
        "I-QUALITY"
      ],
      "pred": [
        "B-TITLE",
        "B-YEAR",
        "B-QUALITY",
        "B-QUALITY"
      ]
    },
    {
      "filename": "Levafan.2014.BluRay.1080p.mkv",
      "preprocessed": "Levafan 2014 BluRay 1080p",
      "true": [
        "B-TITLE",
        "B-YEAR",
        "B-QUALITY",
        "I-QUALITY"
      ],
      "pred": [
        "B-TITLE",
        "B-YEAR",
        "B-QUALITY",
        "B-QUALITY"
      ]
    },
    {
      "filename": "Tool - Lateralus - FLAC.flac",
      "preprocessed": "Tool Lateralus FLAC",
      "true": [
        "B-ARTIST",
        "B-TITLE",
        "B-QUALITY"
      ],
      "pred": [
        "B-TITLE",
        "I-TITLE",
        "B-QUALITY"
      ]
    },
    {
      "filename": "Rage.Against.the.Machine - Killing.in.the.Name - 320.mp3",
      "preprocessed": "Rage Against the Machine Killing in the Name 320",
      "true": [
        "B-ARTIST",
        "I-ARTIST",
        "I-ARTIST",
        "I-ARTIST",
        "B-TITLE",
        "I-TITLE",
        "I-TITLE",
        "I-TITLE",
        "B-QUALITY"
      ],
      "pred": [
        "B-ARTIST",
        "I-TITLE",
        "I-TITLE",
        "I-TITLE",
        "I-TITLE",
        "I-TITLE",
        "I-TITLE",
        "I-TITLE",
        "B-QUALITY"
      ]
    },
    {
      "filename": "Stranger.Things.S04E01.WEB-DL.1080p.mkv",
      "preprocessed": "Stranger Things S04E01 WEB DL 1080p",
      "true": [
        "B-TITLE",
        "I-TITLE",
        "O",
        "B-QUALITY",
        "I-QUALITY",
        "I-QUALITY"
      ],
      "pred": [
        "B-TITLE",
        "I-TITLE",
        "O",
        "B-QUALITY",
        "I-QUALITY",
        "B-QUALITY"
      ]
    },
    {
      "filename": "The Witcher S02E03 4K HDR.mkv",
      "preprocessed": "The Witcher S02E03 4K HDR",
      "true": [
        "B-TITLE",
        "I-TITLE",
        "O",
        "B-QUALITY",
        "O"
      ],
      "pred": [
        "B-TITLE",
        "I-TITLE",
        "O",
        "B-QUALITY",
        "I-QUALITY"
      ]
    },
    {
      "filename": "IMG_20240515_142233.jpg",
      "preprocessed": "IMG 20240515 142233",
      "true": [
        "O",
        "O",
        "O"
      ],
      "pred": [
        "O",
        "B-YEAR",
        "O"
      ]
    },
    {
      "filename": "DSC02145.JPG",
      "preprocessed": "DSC02145",
      "true": [
        "O"
      ],
      "pred": [
        "B-QUALITY"
      ]
    },
    {
      "filename": "2024_отпуск.mp4",
      "preprocessed": "2024 отпуск",
      "true": [
        "B-YEAR",
        "O"
      ],
      "pred": [
        "B-YEAR",
        "B-TITLE"
      ]
    }
  ]
}